netbox_storage_server/__init__.py
netbox_storage_server/py.typed
netbox_storage_server-0.0.8.dist-info/METADATA
netbox_storage_server-0.0.8.dist-info/WHEEL
netbox_storage_server-0.0.8.dist-info/licenses/LICENSE
netbox_storage_server-0.0.8.dist-info/RECORD
