Metadata-Version: 2.4
Name: netbox-storage-server
Version: 0.0.8
Summary: NetBox Storage Server plugin
Author-email: Kenneth Trelborg Vestergaard <6765646+mortencombat@users.noreply.github.com>
License-File: LICENSE
Requires-Python: >=3.12
